mysql_connection_pool/__init__.py
mysql_connection_pool/base.py
mysql_connection_pool/connection.py
mysql_connection_pool/connection_new.py
mysql_connection_pool/logger.py
mysql_connection_pool/mysql_connection_pool.py
mysql_connection_pool/mysql_connection_pool_logger.py
mysql_connection_pool/operations.py
mysql_connection_pool/sql_executor.py
mysql_connection_pool/sql_file_executor.py
mysql_connection_pool-1.1.2.dist-info/licenses/LICENSE
mysql_connection_pool-1.1.2.dist-info/METADATA
mysql_connection_pool-1.1.2.dist-info/WHEEL
mysql_connection_pool-1.1.2.dist-info/top_level.txt
mysql_connection_pool-1.1.2.dist-info/RECORD
