Metadata-Version: 2.4
Name: mysql-connection-pool
Version: 1.1.2
Summary: Una clase para manejar conexiones a MySQL con un pool de conexiones y soporte para múltiples hilos.
Home-page: https://github.com/cursland/mysql_connection_pool
Author: Cursland
Author-email: 
Project-URL: Author, https://cursland.com
Project-URL: GitHub, https://github.com/cursland/mysql_connection_pool
Keywords: mysql database connection pool threading
Classifier: Programming Language :: Python :: 3
Classifier: Programming Language :: Python :: 3.8
Classifier: Programming Language :: Python :: 3.9
Classifier: Programming Language :: Python :: 3.10
Classifier: Programming Language :: Python :: 3.11
Classifier: Programming Language :: Python :: 3.12
Classifier: License :: OSI Approved :: MIT License
Classifier: Operating System :: OS Independent
Classifier: Development Status :: 4 - Beta
Classifier: Intended Audience :: Developers
Classifier: Topic :: Database
Classifier: Topic :: Software Development :: Libraries :: Python Modules
Requires-Python: >=3.8
License-File: LICENSE
Requires-Dist: mysql-connector-python>=8.4.0
Requires-Dist: sqlglot>=25.0.0
Dynamic: author
Dynamic: classifier
Dynamic: description
Dynamic: description-content-type
Dynamic: home-page
Dynamic: keywords
Dynamic: license-file
Dynamic: project-url
Dynamic: requires-dist
Dynamic: requires-python
Dynamic: summary
